pyutilib.svn-1.5.1-py2.7-nspkg.pth
pyutilib/svn/__init__.py
pyutilib/svn/core.py
pyutilib/svn/database.py
pyutilib/svn/external_manager.py
pyutilib/svn/repository.py
pyutilib/svn/svn_timemachine.py
pyutilib/svn/svnpm.py
pyutilib.svn-1.5.1.dist-info/DESCRIPTION.rst
pyutilib.svn-1.5.1.dist-info/entry_points.txt
pyutilib.svn-1.5.1.dist-info/METADATA
pyutilib.svn-1.5.1.dist-info/metadata.json
pyutilib.svn-1.5.1.dist-info/namespace_packages.txt
pyutilib.svn-1.5.1.dist-info/RECORD
pyutilib.svn-1.5.1.dist-info/top_level.txt
pyutilib.svn-1.5.1.dist-info/WHEEL
