Metadata-Version: 2.0
Name: pyutilib.svn
Version: 1.5.1
Summary: A PyUtilib package for subversion-related utilities.
Home-page: https://software.sandia.gov/svn/public/pyutilib/pyutilib.svn
Author: William E. Hart
Author-email: wehart@sandia.gov
License: BSD
Keywords: utility
Platform: any
Classifier: Development Status :: 4 - Beta
Classifier: Intended Audience :: End Users/Desktop
Classifier: License :: OSI Approved :: BSD License
Classifier: Natural Language :: English
Classifier: Operating System :: Microsoft :: Windows
Classifier: Operating System :: Unix
Classifier: Programming Language :: Python
Classifier: Programming Language :: Unix Shell
Classifier: Topic :: Software Development :: Libraries :: Python Modules
